{
  "allow_paper_fidelity_drift": false,
  "allow_reuse_cross_fault": false,
  "campaign_dir": "/Users/aumpandya/Documents/Projects/ads_project/failure-zoo-4/data/experiments/campaign-20260328T235521Z",
  "campaign_id": "20260328T235521Z",
  "comparator_scope": "pca_knn_not_included",
  "compose_config_sha256": "176f295739ee852c3433736f3f1e29a3f597557544919377a8ef9ce04eada555",
  "compose_images": [],
  "dry_run": false,
  "generated_at": 1774742153.3246431,
  "git_branch": "feature/experiments",
  "git_sha": "c0d24cc342cdc19036af7c2164a5279748e5ce76",
  "loadgen_enabled": true,
  "loadgen_ms": 20,
  "loadgen_profile": "steady",
  "loadgen_rps": 4.0,
  "loadgen_seed": 42,
  "matrix_description": "Paper-aligned and extended fault campaigns for UBL-style evaluation.",
  "matrix_name": "ubl_fault_matrix_v1",
  "matrix_path": "experiments/fault_matrix_multiseed_quick.yaml",
  "matrix_seed": 42,
  "matrix_seeds": [
    41,
    42,
    43
  ],
  "mode": "full",
  "platform": "macOS-26.2-arm64-arm-64bit",
  "python_version": "3.10.16",
  "resumed_campaign_dir": "",
  "reuse_learner_if_env_unchanged": false,
  "run_count": 48
}